README.md
setup.py
apache_sedona_beta.egg-info/PKG-INFO
apache_sedona_beta.egg-info/SOURCES.txt
apache_sedona_beta.egg-info/dependency_links.txt
apache_sedona_beta.egg-info/requires.txt
apache_sedona_beta.egg-info/top_level.txt
sedona/__init__.py
sedona/exceptions.py
sedona/version.py
sedona/core/__init__.py
sedona/core/utils.py
sedona/core/SpatialRDD/__init__.py
sedona/core/SpatialRDD/circle_rdd.py
sedona/core/SpatialRDD/linestring_rdd.py
sedona/core/SpatialRDD/point_rdd.py
sedona/core/SpatialRDD/polygon_rdd.py
sedona/core/SpatialRDD/rectangle_rdd.py
sedona/core/SpatialRDD/spatial_rdd.py
sedona/core/SpatialRDD/spatial_rdd_factory.py
sedona/core/enums/__init__.py
sedona/core/enums/file_data_splitter.py
sedona/core/enums/grid_type.py
sedona/core/enums/index_type.py
sedona/core/enums/join_build_side.py
sedona/core/enums/spatial.py
sedona/core/formatMapper/__init__.py
sedona/core/formatMapper/disc_utils.py
sedona/core/formatMapper/geo_json_reader.py
sedona/core/formatMapper/geo_reader.py
sedona/core/formatMapper/wkb_reader.py
sedona/core/formatMapper/wkt_reader.py
sedona/core/formatMapper/shapefileParser/__init__.py
sedona/core/formatMapper/shapefileParser/shape_file_reader.py
sedona/core/geom/__init__.py
sedona/core/geom/circle.py
sedona/core/geom/envelope.py
sedona/core/jvm/__init__.py
sedona/core/jvm/abstract.py
sedona/core/jvm/config.py
sedona/core/jvm/translate.py
sedona/core/spatialOperator/__init__.py
sedona/core/spatialOperator/join_params.py
sedona/core/spatialOperator/join_query.py
sedona/core/spatialOperator/join_query_raw.py
sedona/core/spatialOperator/knn_query.py
sedona/core/spatialOperator/range_query.py
sedona/core/spatialOperator/range_query_raw.py
sedona/core/spatialOperator/rdd.py
sedona/register/__init__.py
sedona/register/geo_registrator.py
sedona/register/java_libs.py
sedona/sql/__init__.py
sedona/sql/exceptions.py
sedona/sql/types.py
sedona/utils/__init__.py
sedona/utils/abstract_parser.py
sedona/utils/adapter.py
sedona/utils/binary_parser.py
sedona/utils/decorators.py
sedona/utils/geometry_adapter.py
sedona/utils/jvm.py
sedona/utils/meta.py
sedona/utils/prep.py
sedona/utils/serde.py
sedona/utils/spatial_rdd_parser.py
sedona/utils/types.py