Metadata-Version: 2.1
Name: apache-sedona-beta
Version: 1.1.1.20211129.1523
Summary: Apache Sedona is a cluster computing system for processing large-scale spatial data
Home-page: https://sedona.apache.org
Author: Apache Sedona
Author-email: dev@sedona.apache.org
License: Apache License v2.0
Project-URL: Documentation, https://sedona.apache.org
Project-URL: Source code, https://github.com/apache/incubator-sedona
Project-URL: Bug Reports, https://issues.apache.org/jira/projects/SEDONA
Platform: UNKNOWN
Classifier: Programming Language :: Python :: 3
Classifier: License :: OSI Approved :: Apache Software License
Requires-Python: >=3.6
Provides-Extra: spark
